LICENSE.txt
MANIFEST.in
README.md
setup.cfg
setup.py
django_media_albums.egg-info/PKG-INFO
django_media_albums.egg-info/SOURCES.txt
django_media_albums.egg-info/dependency_links.txt
django_media_albums.egg-info/requires.txt
django_media_albums.egg-info/top_level.txt
media_albums/__init__.py
media_albums/admin.py
media_albums/apps.py
media_albums/forms.py
media_albums/models.py
media_albums/settings.py
media_albums/urls.py
media_albums/views.py
media_albums/migrations/0001_initial.py
media_albums/migrations/__init__.py
media_albums/static/media_albums/styles/media_albums.css
media_albums/templates/admin/media_albums/userphoto/change_list.html
media_albums/templates/media_albums/album_detail.html
media_albums/templates/media_albums/album_item_detail.html
media_albums/templates/media_albums/album_list.html
media_albums/templates/media_albums/album_pagination.html
media_albums/templates/media_albums/base.html
media_albums/templates/media_albums/item_pagination.html
media_albums/templates/media_albums/upload-success.html
media_albums/templates/media_albums/upload.html
media_albums/templates/media_albums/emails/user_photo_uploaded-subject.txt
media_albums/templates/media_albums/emails/user_photo_uploaded.txt
media_albums/templatetags/__init__.py
media_albums/templatetags/media_albums_tags.py