Metadata-Version: 1.0
Name: django-media-albums
Version: 0.2.0
Summary: A photo/video/audio albums application for Django
Home-page: https://github.com/VelocityWebworks/django-media-albums
Author: Velocity Webworks
Author-email: dev@velocitywebworks.com
License: UNKNOWN
Platform: UNKNOWN
